{"resourceId":"50001","properties":{"process_id":"process","name":"","documentation":"","type":"","process_author":"","process_version":"","process_namespace":"http://www.activiti.org/processdef","executionlisteners":"","eventlisteners":"","signaldefinitions":"","messagedefinitions":""},"stencil":{"id":"BPMNDiagram"},"childShapes":[{"resourceId":"sid-7EBB9A7E-A6B5-48A7-B6C4-49E2B71787CC","properties":{"overrideid":"","name":"","documentation":"","executionlisteners":"","initiator":"","formkeydefinition":"","formproperties":"","events":"","startevent":"","currentscene":""},"stencil":{"id":"StartNoneEvent"},"childShapes":[],"outgoing":[{"resourceId":"sid-C9864710-3779-4935-B276-EAE086BCC140"}],"bounds":{"lowerRight":{"x":195,"y":45},"upperLeft":{"x":165,"y":15}},"dockers":[]},{"resourceId":"sid-C9864710-3779-4935-B276-EAE086BCC140","properties":{"overrideid":"","name":"","documentation":"","conditionsequenceflow":"","executionlisteners":"","condition":"","defaultflow":"false"},"stencil":{"id":"SequenceFlow"},"childShapes":[],"outgoing":[{"resourceId":"sid-0FB7ABBD-CBDF-49C3-809F-6A118891E863"}],"bounds":{"lowerRight":{"x":180,"y":89.9375},"upperLeft":{"x":180,"y":45.0625}},"dockers":[{"x":15,"y":15},{"x":50,"y":40}],"target":{"resourceId":"sid-0FB7ABBD-CBDF-49C3-809F-6A118891E863"}},{"resourceId":"sid-49C1CE7C-9CE6-48C1-9237-5F9F67928D41","properties":{"overrideid":"sid-9DE12449-0549-4100-8CB1-C1A26EF5E36A","name":"用户","documentation":"","type":"用户","owner":"","executionlisteners":"","initiator":"","events":"","services":""},"stencil":{"id":"Person"},"childShapes":[],"outgoing":[],"bounds":{"lowerRight":{"x":495,"y":375},"upperLeft":{"x":465,"y":345}},"dockers":[]},{"resourceId":"sid-8BFF31D5-90E7-41C9-9DF6-22734ADBFAF8","properties":{"overrideid":"sid-45939CC7-EAED-404F-8DCD-6409A512403E","name":"点咖啡应用","documentation":"","type":"云应用","executionlisteners":"","initiator":"","events":"","services":[{"id":"sid-8D5D6CE0-2FED-4A36-9FEA-0CA7D0B24A7C","function":"点咖啡服务"}]},"stencil":{"id":"CloudApp"},"childShapes":[],"outgoing":[],"bounds":{"lowerRight":{"x":505.000003,"y":111.000001},"upperLeft":{"x":465,"y":80.999999}},"dockers":[]},{"resourceId":"sid-0FB7ABBD-CBDF-49C3-809F-6A118891E863","properties":{"overrideid":"sid-8D5D6CE0-2FED-4A36-9FEA-0CA7D0B24A7C","name":"点咖啡服务","actioninputstatus":"","actionoutputstatus":"","documentation":"","activityelement":{"id":"sid-45939CC7-EAED-404F-8DCD-6409A512403E","name":"点咖啡应用","type":"云应用"},"input":"","output":"","animate_direction":"0","currentscene":"","type":"http://b3mn.org/stencilset/bpmn2.0#UndefinedAction"},"stencil":{"id":"CyberAction"},"childShapes":[],"outgoing":[{"resourceId":"sid-EA933EB4-0315-455A-912E-69B71253BF6E"}],"bounds":{"lowerRight":{"x":230,"y":170},"upperLeft":{"x":130,"y":90}},"dockers":[]},{"resourceId":"sid-8DECDA11-179B-4D46-B3B4-0FC3D56D1D92","properties":{"overrideid":"","name":"订单","documentation":"","type":"","executionlisteners":"","initiator":"","events":"","services":""},"stencil":{"id":"CyberObject"},"childShapes":[],"outgoing":[],"bounds":{"lowerRight":{"x":554.0000005,"y":115},"upperLeft":{"x":516.0000025,"y":77}},"dockers":[]},{"resourceId":"sid-EA933EB4-0315-455A-912E-69B71253BF6E","properties":{"overrideid":"","name":"","documentation":"","conditionsequenceflow":"","executionlisteners":"","condition":"","defaultflow":"false"},"stencil":{"id":"SequenceFlow"},"childShapes":[],"outgoing":[{"resourceId":"sid-0ED1F121-A70E-4EAA-B47B-600F33E175C9"}],"bounds":{"lowerRight":{"x":180,"y":214.9375},"upperLeft":{"x":180,"y":170.0625}},"dockers":[{"x":50,"y":40},{"x":50,"y":40}],"target":{"resourceId":"sid-0ED1F121-A70E-4EAA-B47B-600F33E175C9"}},{"resourceId":"sid-65954ED9-DB6F-4931-9D60-7E5141512E4E","properties":{"overrideid":"sid-662C8781-0D5E-4B3C-B562-9D40F1A7111A","name":"咖啡机","documentation":"","type":"设备","ownedbywho":"","executionlisteners":"","initiator":"","events":[{"id":"sid-66265690-965D-4890-A3F6-6C48BA621CD5","event":"咖啡制作完成"}],"services":[{"id":"sid-AE040CD1-4BD8-4661-8C74-A25BFE6D226B","function":"制作咖啡"}]},"stencil":{"id":"Device"},"childShapes":[],"outgoing":[],"bounds":{"lowerRight":{"x":904.1519490000001,"y":325.000002},"upperLeft":{"x":870,"y":285}},"dockers":[]},{"resourceId":"sid-0ED1F121-A70E-4EAA-B47B-600F33E175C9","properties":{"overrideid":"sid-212BC3B8-E6D0-440D-98F7-81B562F3E62B","name":"制作咖啡","actioninputstatus":"","actionoutputstatus":"","documentation":"","activityelement":{"id":"sid-662C8781-0D5E-4B3C-B562-9D40F1A7111A","name":"咖啡机","type":"设备"},"input":"","output":"","animate_direction":"0","currentscene":"","type":"http://b3mn.org/stencilset/bpmn2.0#UndefinedAction"},"stencil":{"id":"PhysicalAction"},"childShapes":[],"outgoing":[{"resourceId":"sid-251F2D80-C1CA-425A-97AB-20E6C70A9F48"}],"bounds":{"lowerRight":{"x":230,"y":295},"upperLeft":{"x":130,"y":215}},"dockers":[]},{"resourceId":"sid-66D19909-E332-478F-8FDA-4A939E5D5032","properties":{"overrideid":"sid-66265690-965D-4890-A3F6-6C48BA621CD5","name":"咖啡制作完成","actioninputstatus":"","actionoutputstatus":"","documentation":"","activityelement":{"id":"sid-662C8781-0D5E-4B3C-B562-9D40F1A7111A","name":"咖啡机","type":"设备"},"input":"","output":"","animate_direction":"0","currentscene":""},"stencil":{"id":"DefaultEvent"},"childShapes":[],"outgoing":[{"resourceId":"sid-6B8E2FD3-D888-4376-B5AC-113F14C55F3C"}],"bounds":{"lowerRight":{"x":230,"y":410},"upperLeft":{"x":130,"y":330}},"dockers":[]},{"resourceId":"sid-251F2D80-C1CA-425A-97AB-20E6C70A9F48","properties":{"overrideid":"","name":"","documentation":"","conditionsequenceflow":"","executionlisteners":"","condition":"","defaultflow":"false"},"stencil":{"id":"SequenceFlow"},"childShapes":[],"outgoing":[{"resourceId":"sid-66D19909-E332-478F-8FDA-4A939E5D5032"}],"bounds":{"lowerRight":{"x":180,"y":329.46875},"upperLeft":{"x":180,"y":295.53125}},"dockers":[{"x":50,"y":40},{"x":50,"y":40}],"target":{"resourceId":"sid-66D19909-E332-478F-8FDA-4A939E5D5032"}},{"resourceId":"sid-6B8E2FD3-D888-4376-B5AC-113F14C55F3C","properties":{"overrideid":"","name":"","documentation":"","conditionsequenceflow":"","executionlisteners":"","condition":"","defaultflow":"false"},"stencil":{"id":"SequenceFlow"},"childShapes":[],"outgoing":[{"resourceId":"sid-5856D9BC-B932-4AF6-B517-1973590C5EBB"}],"bounds":{"lowerRight":{"x":180,"y":454.9375},"upperLeft":{"x":180,"y":410.0625}},"dockers":[{"x":50,"y":40},{"x":50,"y":40}],"target":{"resourceId":"sid-5856D9BC-B932-4AF6-B517-1973590C5EBB"}},{"resourceId":"sid-A9345BA1-D65E-4B9C-B63A-C8D1F0C83B6D","properties":{"overrideid":"sid-BBD9FB7F-AFB5-494B-872F-542E4DA856DF","name":"工人","documentation":"","type":"工人","owner":[],"executionlisteners":"","initiator":"","events":"","services":[{"id":"sid-B9A574B5-C092-4A69-8DA4-4D4E1DE5A156","function":"获取咖啡"},{"id":"sid-E1A976B7-00C6-4C2F-B199-BCBD73305E8C","function":"递交物品"}]},"stencil":{"id":"Person_Worker"},"childShapes":[],"outgoing":[],"bounds":{"lowerRight":{"x":554.3939725000001,"y":387.90482599999996},"upperLeft":{"x":515.6060305000001,"y":352.095174}},"dockers":[]},{"resourceId":"sid-5856D9BC-B932-4AF6-B517-1973590C5EBB","properties":{"overrideid":"sid-B9A574B5-C092-4A69-8DA4-4D4E1DE5A156","name":"获取咖啡","actioninputstatus":[{"id":"sid-BBD9FB7F-AFB5-494B-872F-542E4DA856DF","type":"工人","name":"工人","position":{"x":535.0000015,"y":370}}],"actionoutputstatus":[{"id":"sid-BBD9FB7F-AFB5-494B-872F-542E4DA856DF","type":"工人","name":"工人","position":{"x":844.393971,"y":305.000001}}],"documentation":"","activityelement":{"id":"sid-BBD9FB7F-AFB5-494B-872F-542E4DA856DF","name":"工人","type":"工人"},"input":"","output":"","animate_direction":"0","currentscene":"","type":"http://b3mn.org/stencilset/bpmn2.0#UndefinedAction"},"stencil":{"id":"SocialAction"},"childShapes":[],"outgoing":[{"resourceId":"sid-BE137F68-FC46-413A-9886-291BD5A0B37C"}],"bounds":{"lowerRight":{"x":230,"y":535},"upperLeft":{"x":130,"y":455}},"dockers":[]},{"resourceId":"sid-BE137F68-FC46-413A-9886-291BD5A0B37C","properties":{"overrideid":"","name":"","documentation":"","conditionsequenceflow":"","executionlisteners":"","condition":"","defaultflow":"false"},"stencil":{"id":"SequenceFlow"},"childShapes":[],"outgoing":[{"resourceId":"sid-82F92FAF-BFB4-4CA1-99C9-391FDBEF9633"}],"bounds":{"lowerRight":{"x":180,"y":579.9375},"upperLeft":{"x":180,"y":535.0625}},"dockers":[{"x":50,"y":40},{"x":50,"y":40}],"target":{"resourceId":"sid-82F92FAF-BFB4-4CA1-99C9-391FDBEF9633"}},{"resourceId":"sid-82F92FAF-BFB4-4CA1-99C9-391FDBEF9633","properties":{"overrideid":"sid-E1A976B7-00C6-4C2F-B199-BCBD73305E8C","name":"递交物品","actioninputstatus":[{"id":"sid-BBD9FB7F-AFB5-494B-872F-542E4DA856DF","type":"工人","name":"工人","position":{"x":844.393971,"y":305.000001}},{"id":"sid-662C8781-0D5E-4B3C-B562-9D40F1A7111A","type":"设备","name":"咖啡机","position":{"x":887.0759745,"y":305.000001}}],"actionoutputstatus":[{"id":"sid-BBD9FB7F-AFB5-494B-872F-542E4DA856DF","type":"工人","name":"工人","position":{"x":535.0000015,"y":370}},{"id":"sid-662C8781-0D5E-4B3C-B562-9D40F1A7111A","type":"设备","name":"咖啡","position":{"x":887.0759745,"y":305.000001},"$$hashKey":"34M"}],"documentation":"","activityelement":{"id":"sid-BBD9FB7F-AFB5-494B-872F-542E4DA856DF","name":"工人","type":"工人"},"input":"","output":"","animate_direction":"0","currentscene":"","type":"http://b3mn.org/stencilset/bpmn2.0#UndefinedAction"},"stencil":{"id":"SocialAction"},"childShapes":[],"outgoing":[],"bounds":{"lowerRight":{"x":230,"y":660},"upperLeft":{"x":130,"y":580}},"dockers":[]}],"bounds":{"lowerRight":{"x":1200,"y":1050},"upperLeft":{"x":0,"y":0}},"stencilset":{"url":"stencilsets/bpmn2.0/bpmn2.0.json","namespace":"http://b3mn.org/stencilset/bpmn2.0#"},"ssextensions":[]}