{"resourceId":"95001","properties":{"process_id":"process","name":"小智热水壶烧水","documentation":"","type":"","process_author":"","process_version":"","process_namespace":"http://www.activiti.org/processdef","executionlisteners":"","eventlisteners":"","signaldefinitions":"","messagedefinitions":""},"stencil":{"id":"BPMNDiagram"},"childShapes":[{"resourceId":"sid-4DE5F282-6E93-4CC0-8290-F1E3760AE8D7","properties":{"overrideid":"","name":"","documentation":"","executionlisteners":"","initiator":"","formkeydefinition":"","formproperties":"","events":"","startevent":"","currentscene":""},"stencil":{"id":"StartNoneEvent"},"childShapes":[],"outgoing":[{"resourceId":"sid-28079C23-4450-4BDA-881F-7EC8CD37AE66"}],"bounds":{"lowerRight":{"x":185,"y":45},"upperLeft":{"x":155,"y":15}},"dockers":[]},{"resourceId":"sid-28079C23-4450-4BDA-881F-7EC8CD37AE66","properties":{"overrideid":"","name":"","documentation":"","conditionsequenceflow":"","executionlisteners":"","condition":"","defaultflow":"false"},"stencil":{"id":"SequenceFlow"},"childShapes":[],"outgoing":[{"resourceId":"sid-CA80FC5C-83A6-4402-9F78-F64D48B5D8B8"}],"bounds":{"lowerRight":{"x":170,"y":89.9375},"upperLeft":{"x":170,"y":45.0625}},"dockers":[{"x":15,"y":15},{"x":50,"y":40}],"target":{"resourceId":"sid-CA80FC5C-83A6-4402-9F78-F64D48B5D8B8"}},{"resourceId":"sid-4EBEA5EC-B866-4038-8B3C-780F2C4DB9EE","properties":{"overrideid":"sid-71D070E6-A6B1-40F2-A054-8673C3450C3B","name":"小智热水壶","documentation":"","type":"设备","ownedbywho":"","executionlisteners":"","initiator":"","events":"","services":[{"id":"sid-CCAF111B-C296-4096-B50C-08B5E4BA6D90","function":"烧水"}]},"stencil":{"id":"Device"},"childShapes":[],"outgoing":[],"bounds":{"lowerRight":{"x":679.0759745,"y":361.000001},"upperLeft":{"x":644.9240255,"y":320.999999}},"dockers":[]},{"resourceId":"sid-CA80FC5C-83A6-4402-9F78-F64D48B5D8B8","properties":{"overrideid":"sid-CCAF111B-C296-4096-B50C-08B5E4BA6D90","name":"烧水","actioninputstatus":[{"id":"sid-FC853682-66FE-4452-A0A7-F74394934D1D","name":"","position":{"x":180,"y":30}}],"actionoutputstatus":"","documentation":"","activityelement":{},"input":"","output":"","animate_direction":"0","currentscene":"","resourceline":[],"type":"http://b3mn.org/stencilset/bpmn2.0#UndefinedAction"},"stencil":{"id":"PhysicalAction"},"childShapes":[],"outgoing":[],"bounds":{"lowerRight":{"x":220,"y":170},"upperLeft":{"x":120,"y":90}},"dockers":[]}],"bounds":{"lowerRight":{"x":1200,"y":1050},"upperLeft":{"x":0,"y":0}},"stencilset":{"url":"stencilsets/bpmn2.0/bpmn2.0.json","namespace":"http://b3mn.org/stencilset/bpmn2.0#"},"ssextensions":[]}